facesign/__init__.py
facesign/client.py
facesign/api/__init__.py
facesign/api/avatars.py
facesign/api/languages.py
facesign/api/sessions.py
facesign/models/__init__.py
facesign/models/common.py
facesign/models/errors.py
facesign/models/nodes.py
facesign/models/sessions.py
facesign/utils/__init__.py
facesign/utils/helpers.py
facesign_api-1.0.19.dist-info/licenses/LICENSE
facesign_api-1.0.19.dist-info/METADATA
facesign_api-1.0.19.dist-info/WHEEL
facesign_api-1.0.19.dist-info/top_level.txt
facesign_api-1.0.19.dist-info/RECORD
